immoscout_scraper/__init__.py
immoscout_scraper/__main__.py
immoscout_scraper/cli.py
immoscout_scraper/db.py
immoscout_scraper/models.py
immoscout_scraper/scrape.py
immoscout_scraper/url_conversion.py
immoscout_scraper-1.1.1.dist-info/METADATA
immoscout_scraper-1.1.1.dist-info/WHEEL
immoscout_scraper-1.1.1.dist-info/entry_points.txt
immoscout_scraper-1.1.1.dist-info/licenses/LICENSE
immoscout_scraper-1.1.1.dist-info/RECORD
