Metadata-Version: 2.4
Name: immoscout-scraper
Version: 1.1.1
Summary: Scrapes rental properties listed on www.immoscout24.de
Project-URL: Homepage, https://libklein.github.io/immoscout-scraper/
Project-URL: Repository, https://github.com/libklein/immoscout-scraper
Project-URL: Documentation, https://libklein.github.io/immoscout-scraper/
Author-email: Patrick Klein <patrick@libklein.com>
License-File: LICENSE
Keywords: python
Classifier: Intended Audience :: Developers
Classifier: Programming Language :: Python
Classifier: Programming Language :: Python :: 3
Classifier: Programming Language :: Python :: 3.10
Classifier: Programming Language :: Python :: 3.11
Classifier: Programming Language :: Python :: 3.12
Classifier: Programming Language :: Python :: 3.13
Classifier: Topic :: Software Development :: Libraries :: Python Modules
Requires-Python: <4.0,>=3.10
Requires-Dist: aiolimiter>=1.2.1
Requires-Dist: furl>=2.1.4
Requires-Dist: pydantic>=2.11.5
Requires-Dist: rnet>=2.2.11
Requires-Dist: sqlmodel>=0.0.24
Requires-Dist: tenacity>=9.1.2
Requires-Dist: typer>=0.16.0
